agentctlx/__init__.py
agentctlx/cli.py
agentctlx-0.1.6.dist-info/WHEEL
agentctlx-0.1.6.dist-info/entry_points.txt
agentctlx-0.1.6.dist-info/METADATA
agentctlx-0.1.6.dist-info/RECORD
