Metadata-Version: 2.3
Name: agentctlx
Version: 0.1.6
Summary: Add your description here
Requires-Dist: click>=8.3.1
Requires-Dist: fastapi>=0.128.0
Requires-Dist: rich>=14.2.0
Requires-Dist: toml>=0.10.2
Requires-Dist: twine>=6.2.0
Requires-Python: >=3.12
